sqlab/__init__.py
sqlab/__main__.py
sqlab/cmd_create.py
sqlab/cmd_parse.py
sqlab/cmd_report.py
sqlab/cmd_shell.py
sqlab/compose_inserts.py
sqlab/config.py
sqlab/database.py
sqlab/dbms/__init__.py
sqlab/dbms/duckdb/__init__.py
sqlab/dbms/mysql/__init__.py
sqlab/dbms/mysql/database.py
sqlab/dbms/mysql/salt.sql
sqlab/dbms/mysql/sqlab_ddl.sql
sqlab/dbms/mysql/triggers.sql
sqlab/dbms/mysql/udf.sql
sqlab/dbms/postgresql/__init__.py
sqlab/dbms/postgresql/database.py
sqlab/dbms/postgresql/salt.sql
sqlab/dbms/postgresql/sqlab_ddl.sql
sqlab/dbms/postgresql/triggers.sql
sqlab/dbms/postgresql/udf.sql
sqlab/dbms/sqlite/__init__.py
sqlab/dbms/sqlite/database.py
sqlab/dbms/sqlite/nb_tools.py
sqlab/dbms/sqlite/salt.sql
sqlab/dbms/sqlite/sqlab_ddl.sql
sqlab/dbms/sqlite/triggers.sql
sqlab/dbms/sqlite/udf.sql
sqlab/generate_messages.py
sqlab/nb_tools.py
sqlab/retrieve_formulas_and_queries.py
sqlab/run_notebook.py
sqlab/sql_tools.py
sqlab/text_tools.py
sqlab/token_table.py
sqlab-0.6.6.dist-info/LICENSE
sqlab-0.6.6.dist-info/WHEEL
sqlab-0.6.6.dist-info/entry_points.txt
sqlab-0.6.6.dist-info/METADATA
sqlab-0.6.6.dist-info/RECORD
